oe_databank/__init__.py
oe_databank/async_client.py
oe_databank/client.py
oe_databank/enums.py
oe_databank/models.py
oe_databank/utils.py
oe_databank-0.2.0.dist-info/METADATA
oe_databank-0.2.0.dist-info/WHEEL
oe_databank-0.2.0.dist-info/licenses/LICENSE
oe_databank-0.2.0.dist-info/RECORD
