Metadata-Version: 2.4
Name: oe-databank
Version: 0.2.0
Summary: A Python client for Oxford Economics' Databank API.
Author: Dominic Tarro
License-File: LICENSE
Requires-Python: >=3.10
Requires-Dist: httpx>=0.27.2
Requires-Dist: orjson>=3.10.7
Requires-Dist: pydantic-settings>=2.0.0
Requires-Dist: pydantic>=2.0.0
Requires-Dist: tenacity>=9.0.0
